{
  "agent_id": "E6",
  "task_description": "多图融合任务描述：将多张图片的元素创意组合成新图片",
  "input_data": {
    "source_images": [
      "第一张素材图片路径或URL",
      "第二张素材图片路径或URL",
      "第三张素材图片路径或URL"
    ],
    "fusion_type": "融合类型：element_extraction（元素提取融合）、style_blend（风格混合）、creative_montage（创意蒙太奇）",
    "fusion_config": {
      "main_image_index": 0,
      "fusion_prompt": "融合指导文字，例如：将所有食材自然地组合在一个火锅中",
      "preserve_quality": true,
      "composition_style": "构图风格：natural（自然）、artistic（艺术化）、commercial（商业化）"
    }
  },
  "output_settings": {
    "save_path": "output/images/e6-creative-combination/",
    "format": "png"
  },
  "metadata": {
    "created_at": "YYYY-MM-DDTHH:MM:SS",
    "created_by": "智能体名称或用户名",
    "version": "1.0"
  }
}
